bioql/__init__.py
bioql/adme_predictor.py
bioql/advanced_qec.py
bioql/auditable_logs.py
bioql/batcher.py
bioql/billing_integration.py
bioql/bio_interpreter.py
bioql/bioisostere_db.py
bioql/cache.py
bioql/chemistry_qec.py
bioql/cli.py
bioql/cloud_auth.py
bioql/compiler.py
bioql/dashboard.py
bioql/drug_designer.py
bioql/drug_designer_v2.py
bioql/drug_discovery_templates.py
bioql/dynamic_bridge.py
bioql/enhanced_quantum.py
bioql/error_mitigation.py
bioql/logger.py
bioql/mapper.py
bioql/molecular_benchmarks.py
bioql/molecular_hamiltonian.py
bioql/molecular_utils.py
bioql/offtarget_panel.py
bioql/optimizer.py
bioql/pdb_generator.py
bioql/pipeline_orchestrator.py
bioql/profiler.py
bioql/provenance.py
bioql/qualtran_qec.py
bioql/quantum_chemistry.py
bioql/quantum_connector.py
bioql/quantum_fusion.py
bioql/remote_execution.py
bioql/resistance_profiler.py
bioql/similarity_search.py
bioql/simple_billing.py
bioql/tiered_billing.py
bioql/benchmarks/__init__.py
bioql/benchmarks/chemistry.py
bioql/benchmarks/quantum_advantage/__init__.py
bioql/benchmarks/quantum_advantage/accuracy_metrics.py
bioql/benchmarks/quantum_advantage/automated_runner.py
bioql/benchmarks/quantum_advantage/benchmark_suite.py
bioql/benchmarks/quantum_advantage/demo_benchmark.py
bioql/benchmarks/quantum_advantage/dft_comparison.py
bioql/benchmarks/quantum_advantage/performance_metrics.py
bioql/benchmarks/quantum_advantage/results_reporter.py
bioql/benchmarks/quantum_advantage/test_benchmarks.py
bioql/chem/__init__.py
bioql/chem/geometry 2.py
bioql/chem/geometry.py
bioql/chem/ligand_prep.py
bioql/chem/neutralize.py
bioql/chem/pharma_scores.py
bioql/chem/receptor_prep.py
bioql/circuits/__init__.py
bioql/circuits/base.py
bioql/circuits/catalog.py
bioql/circuits/algorithms/__init__.py
bioql/circuits/algorithms/grover.py
bioql/circuits/algorithms/vqe.py
bioql/circuits/composition/__init__.py
bioql/circuits/composition/composer.py
bioql/circuits/composition/modular.py
bioql/circuits/composition/stitching.py
bioql-7.0.1.dist-info/licenses/LICENSE
bioql-7.0.1.dist-info/METADATA
bioql-7.0.1.dist-info/WHEEL
bioql-7.0.1.dist-info/entry_points.txt
bioql-7.0.1.dist-info/top_level.txt
bioql-7.0.1.dist-info/RECORD
