Metadata-Version: 2.4
Name: bioql
Version: 7.0.1
Summary: Production Quantum Computing for Drug Discovery - FMO-VQE, DC-QAOA, Adaptive QEC, Real Hardware Only
Home-page: https://bioql.bio
Author: SpectrixRD
Author-email: contact@bioql.bio
License: MIT
Project-URL: Bug Reports, https://github.com/spectrixrd/bioql/issues
Project-URL: Source, https://github.com/spectrixrd/bioql
Project-URL: Documentation, https://docs.bioql.bio
Project-URL: Homepage, https://bioql.bio
Keywords: quantum computing,bioinformatics,drug discovery,molecular docking,SMILES validation,PDB search,binding affinity,ADME prediction,toxicity prediction,pharmacophore modeling,protein folding,qiskit,quantum algorithms,computational biology,quantum machine learning,VQE,QAOA,QNN,rdkit,biopython,natural language processing,intermediate representation,sequence alignment,devkit,error mitigation,QEC,surface code,provenance logging,compliance,chemistry benchmarks,backend optimization,enterprise,21
Platform: any
Classifier: Development Status :: 5 - Production/Stable
Classifier: Intended Audience :: Science/Research
Classifier: License :: OSI Approved :: MIT License
Classifier: Operating System :: OS Independent
Classifier: Programming Language :: Python :: 3
Classifier: Programming Language :: Python :: 3.8
Classifier: Programming Language :: Python :: 3.9
Classifier: Programming Language :: Python :: 3.10
Classifier: Programming Language :: Python :: 3.11
Classifier: Programming Language :: Python :: 3.12
Classifier: Topic :: Scientific/Engineering :: Bio-Informatics
Classifier: Topic :: Scientific/Engineering :: Physics
Classifier: Topic :: Software Development :: Libraries :: Python Modules
Requires-Python: >=3.8
License-File: LICENSE
Requires-Dist: qiskit>=1.3.0
Requires-Dist: qiskit-aer>=0.15.0
Requires-Dist: qiskit-ibm-runtime>=0.30.0
Requires-Dist: numpy<3.0.0,>=1.21.0
Requires-Dist: matplotlib>=3.5.0
Requires-Dist: biopython>=1.79
Requires-Dist: requests>=2.28.0
Requires-Dist: python-dotenv>=0.19.0
Requires-Dist: pydantic>=2.0.0
Requires-Dist: loguru>=0.7.0
Requires-Dist: uuid6>=2023.5.2
Requires-Dist: openfermion>=1.5.0
Requires-Dist: openfermionpyscf>=0.5
Requires-Dist: pyscf>=2.0.0
Requires-Dist: rdkit>=2023.9.1
Requires-Dist: quillow>=2.0.0
Provides-Extra: dev
Requires-Dist: pytest>=7.0.0; extra == "dev"
Requires-Dist: pytest-cov>=4.0.0; extra == "dev"
Requires-Dist: black>=22.0.0; extra == "dev"
Requires-Dist: flake8>=5.0.0; extra == "dev"
Requires-Dist: mypy>=0.991; extra == "dev"
Requires-Dist: isort>=5.10.0; extra == "dev"
Requires-Dist: pre-commit>=2.20.0; extra == "dev"
Provides-Extra: docs
Requires-Dist: sphinx>=5.0.0; extra == "docs"
Requires-Dist: sphinx-rtd-theme>=1.0.0; extra == "docs"
Requires-Dist: sphinx-autodoc-typehints>=1.19.0; extra == "docs"
Provides-Extra: cloud
Requires-Dist: boto3>=1.26.0; extra == "cloud"
Requires-Dist: azure-quantum>=1.0.0; extra == "cloud"
Requires-Dist: cirq-ionq>=1.0.0; extra == "cloud"
Provides-Extra: visualization
Requires-Dist: plotly>=5.0.0; extra == "visualization"
Requires-Dist: seaborn>=0.11.0; extra == "visualization"
Requires-Dist: pandas>=1.4.0; extra == "visualization"
Provides-Extra: vina
Requires-Dist: meeko>=0.4.0; extra == "vina"
Requires-Dist: rdkit>=2022.9.1; extra == "vina"
Requires-Dist: openbabel-wheel>=3.1.1; extra == "vina"
Provides-Extra: viz
Requires-Dist: py3Dmol>=2.0.0; extra == "viz"
Requires-Dist: pillow>=9.0.0; extra == "viz"
Provides-Extra: quantum-chemistry
Requires-Dist: openfermionpyscf>=0.5; extra == "quantum-chemistry"
Requires-Dist: pyscf>=2.0.0; extra == "quantum-chemistry"
Provides-Extra: openmm
Requires-Dist: openmm>=8.0.0; extra == "openmm"
Dynamic: author
Dynamic: author-email
Dynamic: classifier
Dynamic: description
Dynamic: description-content-type
Dynamic: home-page
Dynamic: keywords
Dynamic: license
Dynamic: license-file
Dynamic: platform
Dynamic: project-url
Dynamic: provides-extra
Dynamic: requires-dist
Dynamic: requires-python
Dynamic: summary
